{
  "markers": [
    {
      "markerType": "image",
      "markerSource": "stones.png",
      "resourceName": "Lingua dei Rolling Stones",
      "resourceCaption": "•Il leggendario logo “Tongue & Lip” comprare la prima volta nel marzo 1971 sui VIP Pass di un concerto degli Stones a Londra. La prima comparsa in un album (Stick Fingers) è invece nell’aprile dello stesso anno.      •Già conosciuti e seguiti, nel ’70 i Rolling Stones cercano alla Royal College of Art un artista che crei il logo da usare nei poster del loro imminente tour europeo. Mick Jagger rifiuta il primo disegno del giovane John Pasche; ma il secondo verrà considerato da molti il logo più famoso, potente e iconico della musica rock e degli anni 70 in generale.      •Contrariamente all’opinione comune, il logo non riproduce le labbra di Jagger, ma la bocca della divinità indù Kali.",
      "longitude": 1.6001687401603037,
      "latitude": 0.16980682565002692
    },
    {
      "markerType": "product",
      "markerSource": "45-giri-pink-floyd-1979",
      "longitude": 3.123566088900193,
      "latitude": -0.2367346414750382
    }
  ]
}